{
    "team": [
        {
            "team_name" : "Boston Uprising",
            "team_code" : "BOS",
            "games_played" : 0,
            "games_won" : 0,
            "games_draw" : 0,
            "games_lost" : 0,
            "goals_for" : 0,
            "goals_against" : 0,
            "goal_saldo" : 0,
            "total_points" : 0,
            "players" : ["Neko", "Striker", "AimGod", "Kellex", "Gamsu", "NotE"],
            "logo" : "images/team_logos/boston_uprising.png"
        },
        {
            "team_name" : "Dallas Fuel",
            "team_code" : "DAL",
            "games_played" : 0,
            "games_won" : 0,
            "games_draw" : 0,
            "games_lost" : 0,
            "goals_for" : 0,
            "goals_against" : 0,
            "goal_saldo" : 0,
            "total_points" : 0,
            "players" : ["HarryHook", "Mickie", "aKm", "Unkoe", "OGE", "Taimou", "EFFECT"],
            "logo" : "images/team_logos/dallas_fuel.png"
        },
        {
            "team_name" : "Florida Mayhem",
            "team_code" : "FLA",
            "games_played" : 0,
            "games_won" : 0,
            "games_draw" : 0,
            "games_lost" : 0,
            "goals_for" : 0,
            "goals_against" : 0,
            "goal_saldo" : 0,
            "total_points" : 0,
            "players" : ["Sayaplayer", "TviQ", "XepheR", "aWesomeGuy"],
            "logo" : "images\team_logos\florida_mayhem.png" 
        },
        {
            "team_name" : "Houston Outlaws",
            "team_code" : "HOU",
            "games_played" : 0,
            "games_won" : 0,
            "games_draw" : 0,
            "games_lost" : 0,
            "goals_for" : 0,
            "goals_against" : 0,
            "goal_saldo" : 0,
            "total_points" : 0,
            "players" : ["Muma", "Bani", "SPREE", "Arhan", "Boink", "Rawkus", "LiNkzr", "Jake", "Coolmatt"],
            "logo" : "images/team_logos/houston_outlaws.png"
        },
        {
            "team_name" : "London Spitfire",
            "team_code" : "LON",
            "games_played" : 0,
            "games_won" : 0,
            "games_draw" : 0,
            "games_lost" : 0,
            "goals_for" : 0,
            "goals_against" : 0,
            "goal_saldo" : 0,
            "total_points" : 0,
            "players" : ["Gesture", "birdring", "Bdosin", "NUS", "Fury", "Profit", "Closer"],
            "logo" : "images/team_logos/london_spitfire.png"
        },
        {
            "team_name" : "Los Angeles Gladiators",
            "team_code" : "GLA",
            "games_played" : 0,
            "games_won" : 0,
            "games_draw" : 0,
            "games_lost" : 0,
            "goals_for" : 0,
            "goals_against" : 0,
            "goal_saldo" : 0,
            "total_points" : 0,
            "players" : ["Surefour", "Void", "Bischu", "Shaz", "Hydration", "BigGoose"],
            "logo" : "images/team_logos/los_angeles_gladiators.png"
        },
        {
            "team_name" : "Los Angeles Valiant",
            "team_code" : "VAL",
            "games_played" : 0,
            "games_won" : 0,
            "games_draw" : 0,
            "games_lost" : 0,
            "goals_for" : 0,
            "goals_against" : 0,
            "goal_saldo" : 0,
            "total_points" : 0,
            "players" : ["Kariv", "Bunny", "Fate", "Custa", "Space", "Kuki", "KSF", "Izayaki", "Agilities", "Soon"],
            "logo" : "images/team_logos/los_angeles_valiant.png"
        },
        {
            "team_name" : "New York Excelsior",
            "team_code" : "NYE",
            "games_played" : 0,
            "games_won" : 0,
            "games_draw" : 0,
            "games_lost" : 0,
            "goals_for" : 0,
            "goals_against" : 0,
            "goal_saldo" : 0,
            "total_points" : 0,
            "players" : ["Saebyeolbe", "Meko", "Anamo", "Pine", "Jjonak", "Mano", "Libero", "Ark"],
            "logo" : "images/team_logos/new_york_excelsior.png"
        },
        {
            "team_name" : "Philadelphia Fusion",
            "team_code" : "PHI",
            "games_played" : 0,
            "games_won" : 0,
            "games_draw" : 0,
            "games_lost" : 0,
            "goals_for" : 0,
            "goals_against" : 0,
            "goal_saldo" : 0,
            "total_points" : 0,
            "players" : ["Boombox", "Hotba", "Poko", "Carpe", "Snillo", "SADO", "fragi", "Eqo", "Neptuno"],
            "logo" : "images/team_logos/philadelphia_fusion.png"
        },
        {
            "team_name" : "San Francisco Shock",
            "team_code" : "SFS",
            "games_played" : 0,
            "games_won" : 0,
            "games_draw" : 0,
            "games_lost" : 0,
            "goals_for" : 0,
            "goals_against" : 0,
            "goal_saldo" : 0,
            "total_points" : 0,
            "players" : ["Choihyobin", "Moth", "super", "BABYBAY", "sinatraa", "sleepy", "Danteh", "Nevix", "Architect"],
            "logo" : "images/team_logos/hsan_francisco_shock.png"
        },
        {
            "team_name" : "Seoul Dynasty",
            "team_code" : "SEO",
            "games_played" : 0,
            "games_won" : 0,
            "games_draw" : 0,
            "games_lost" : 0,
            "goals_for" : 0,
            "goals_against" : 0,
            "goal_saldo" : 0,
            "total_points" : 0,
            "players" : ["ryujehong", "Fissure", "ZUNBA", "Munchkin", "FLETA", "tobi"],
            "logo" : "images/team_logos/seoul_dynasty.png"
        },
        {
            "team_name" : "Shanghai Dragons",
            "team_code" : "SHO",
            "games_played" : 0,
            "games_won" : 0,
            "games_draw" : 0,
            "games_lost" : 0,
            "goals_for" : 0,
            "goals_against" : 0,
            "goal_saldo" : 0,
            "total_points" : 0,
            "players" : ["Geguri", "Diya", "Fearless"],
            "logo" : "images/team_logos/shanghai_dragons.png"
        }
    ], 
    "schedule" : 
        {
            "September" : [
                {
                    "home_party" : "SFS",
                    "away_party" : "VAL",
                    "location" : "AJ Katzenmaier",
                    "field" : "1",
                    "game_time" : "9:30 a.m.",
                    "referee" : "John Johnsen",
                    "date" : "September 1th"
                },
                {
                    "home_party" : "SHO",
                    "away_party" : "GLA",
                    "location" : "Greenbay",
                    "field" : "2",
                    "game_time" : "1:00 p.m.",
                    "referee" : "Dick Dicksen",
                    "date" : "September 1th"
                },
                {
                    "home_party" : "DAL",
                    "away_party" : "SEO",
                    "location" : "Howard A Yeager",
                    "field" : "1",
                    "game_time" : "9:30 a.m.",
                    "referee" : "Bob Bobsen",
                    "date" : "September 8th"
                },
                {
                    "home_party" : "LON",
                    "away_party" : "FLA",
                    "location" : "Marjorie P Hart",
                    "field" : "4",
                    "game_time" : "1:00 p.m.",
                    "referee" : "John Johnsen",
                    "date" : "September 8th"
                },
                {
                    "home_party" : "PHI",
                    "away_party" : "HOU",
                    "location" : "North",
                    "field" : "1",
                    "game_time" : "9:30 a.m.",
                    "referee" : "Dick Dicksen",
                    "date" : "September 15th"
                },
                {
                    "home_party" : "BOS",
                    "away_party" : "NYE",
                    "location" : "AJ Katzenmaier",
                    "field" : "2",
                    "game_time" : "9:30 a.m.",
                    "referee" : "Bob Bobsen",
                    "date" : "September 15th"
                },
                {
                    "home_party" : "VAL",
                    "away_party" : "DAL",
                    "location" : "South",
                    "field" : "1",
                    "game_time" : "1:00 p.m.",
                    "referee" : "John Johnsen",
                    "date" : "September 22th"
                },
                {
                    "home_party" : "FLA",
                    "away_party" : "BOS",
                    "location" : "Howard A Yeager",
                    "field" : "2",
                    "game_time" : "9:30 a.m.",
                    "referee" : "Dick Dicksen",
                    "date" : "September 22th"
                },
                {
                    "home_party" : "SFS",
                    "away_party" : "SHO",
                    "location" : "Greenbay",
                    "field" : "1",
                    "game_time" : "9:30 a.m.",
                    "referee" : "Bob Bobsen",
                    "date" : "September 29th"
                }
            ],
            "October" : [
                {
                    "home_party" : "SFS",
                    "away_party" : "PHI",
                    "location" : "Marjonie P Hart",
                    "field" : "2",
                    "game_time" : "9:30 a.m.",
                    "referee" : "Dick Dicksen",
                    "date" : "October 6th"
                },
                {
                    "home_party" : "FLA",
                    "away_party" : "SEO",
                    "location" : "South",
                    "field" : "1",
                    "game_time" : "1:00 p.m.",
                    "referee" : "Bob Bobsen",
                    "date" : "October 6th"
                },
                {
                    "home_party" : "HOU",
                    "away_party" : "SHO",
                    "location" : "Howard A Yeager",
                    "field" : "4",
                    "game_time" : "9:30 a.m.",
                    "referee" : "John Johnsen",
                    "date" : "October 13th"
                },
                {
                    "home_party" : "DAL",
                    "away_party" : "HOU",
                    "location" : "Greenbay",
                    "field" : "1",
                    "game_time" : "1:00 p.m.",
                    "referee" : "Dick Dicksen",
                    "date" : "October 13th"
                },
                {
                    "home_party" : "NYE",
                    "away_party" : "VAL",
                    "location" : "North",
                    "field" : "2",
                    "game_time" : "9:30 a.m.",
                    "referee" : "Bob Bobsen",
                    "date" : "October 20th"
                },
                {
                    "home_party" : "SEO",
                    "away_party" : "BOS",
                    "location" : "Marjorie P Hart",
                    "field" : "1",
                    "game_time" : "1:00 p.m.",
                    "referee" : "John Johnsen",
                    "date" : "October 20th"
                },
                {
                    "home_party" : "SHO",
                    "away_party" : "FLA",
                    "location" : "AJ Katzenmaier",
                    "field" : "3",
                    "game_time" : "9:30 a.m.",
                    "referee" : "Dick Dicksen",
                    "date" : "October 27th"
                },        
                {
                    "home_party" : "LON",
                    "away_party" : "DAL",
                    "location" : "Greenbay",
                    "field" : "1",
                    "game_time" : "1:00 p.m.",
                    "referee" : "Bob Bobsen",
                    "date" : "October 27th"
                }
            ]
        },
    "news" : [
        {
            "title" : "Spitfire spits on the Shocks",
            "article" : "Lorem ipsum dolor sit amet, consectetur adipiscing elit. Donec porta arcu sem, tempus scelerisque dolor euismod fermentum. Nullam sodales, orci volutpat scelerisque posuere, arcu tortor lobortis diam, a porta ante leo ac ex. Sed eget mauris vel nunc pulvinar ultrices vel ut dolor. Proin egestas gravida nulla. Orci varius natoque penatibus et magnis dis parturient montes, nascetur ridiculus mus. Aenean dignissim neque sit amet sagittis convallis. Suspendisse vel diam magna. Donec sit amet nisi nisi. Ut tempus posuere nibh, ac condimentum justo commodo vitae. Suspendisse quis enim sit amet libero volutpat interdum ut ut dolor. Integer condimentum, lacus in dignissim fringilla, ligula felis mattis lectus, eu condimentum neque lorem a mi."
        },
        {
            "title" : "Dynasty slips pass Outlaws",
            "article" : "Lorem ipsum dolor sit amet, consectetur adipiscing elit. Donec porta arcu sem, tempus scelerisque dolor euismod fermentum. Nullam sodales, orci volutpat scelerisque posuere, arcu tortor lobortis diam, a porta ante leo ac ex. Sed eget mauris vel nunc pulvinar ultrices vel ut dolor. Proin egestas gravida nulla. Orci varius natoque penatibus et magnis dis parturient montes, nascetur ridiculus mus. Aenean dignissim neque sit amet sagittis convallis. Suspendisse vel diam magna. Donec sit amet nisi nisi. Ut tempus posuere nibh, ac condimentum justo commodo vitae. Suspendisse quis enim sit amet libero volutpat interdum ut ut dolor. Integer condimentum, lacus in dignissim fringilla, ligula felis mattis lectus, eu condimentum neque lorem a mi."
        },
        {
            "title" : "Late win for Boston Fuel",
            "article" : "Lorem ipsum dolor sit amet, consectetur adipiscing elit. Donec porta arcu sem, tempus scelerisque dolor euismod fermentum. Nullam sodales, orci volutpat scelerisque posuere, arcu tortor lobortis diam, a porta ante leo ac ex. Sed eget mauris vel nunc pulvinar ultrices vel ut dolor. Proin egestas gravida nulla. Orci varius natoque penatibus et magnis dis parturient montes, nascetur ridiculus mus. Aenean dignissim neque sit amet sagittis convallis. Suspendisse vel diam magna. Donec sit amet nisi nisi. Ut tempus posuere nibh, ac condimentum justo commodo vitae. Suspendisse quis enim sit amet libero volutpat interdum ut ut dolor. Integer condimentum, lacus in dignissim fringilla, ligula felis mattis lectus, eu condimentum neque lorem a mi."
        },
        {
            "title" : "Valiants takes down the Gladiators",
            "article" : "Lorem ipsum dolor sit amet, consectetur adipiscing elit. Donec porta arcu sem, tempus scelerisque dolor euismod fermentum. Nullam sodales, orci volutpat scelerisque posuere, arcu tortor lobortis diam, a porta ante leo ac ex. Sed eget mauris vel nunc pulvinar ultrices vel ut dolor. Proin egestas gravida nulla. Orci varius natoque penatibus et magnis dis parturient montes, nascetur ridiculus mus. Aenean dignissim neque sit amet sagittis convallis. Suspendisse vel diam magna. Donec sit amet nisi nisi. Ut tempus posuere nibh, ac condimentum justo commodo vitae. Suspendisse quis enim sit amet libero volutpat interdum ut ut dolor. Integer condimentum, lacus in dignissim fringilla, ligula felis mattis lectus, eu condimentum neque lorem a mi."
        },
        {
            "title" : "Dalles Fuel ignites the Mayhem",
            "article" : "Lorem ipsum dolor sit amet, consectetur adipiscing elit. Donec porta arcu sem, tempus scelerisque dolor euismod fermentum. Nullam sodales, orci volutpat scelerisque posuere, arcu tortor lobortis diam, a porta ante leo ac ex. Sed eget mauris vel nunc pulvinar ultrices vel ut dolor. Proin egestas gravida nulla. Orci varius natoque penatibus et magnis dis parturient montes, nascetur ridiculus mus. Aenean dignissim neque sit amet sagittis convallis. Suspendisse vel diam magna. Donec sit amet nisi nisi. Ut tempus posuere nibh, ac condimentum justo commodo vitae. Suspendisse quis enim sit amet libero volutpat interdum ut ut dolor. Integer condimentum, lacus in dignissim fringilla, ligula felis mattis lectus, eu condimentum neque lorem a mi."
        },
        {
            "title" : "Dynasty takes the win",
            "article" : "Lorem ipsum dolor sit amet, consectetur adipiscing elit. Donec porta arcu sem, tempus scelerisque dolor euismod fermentum. Nullam sodales, orci volutpat scelerisque posuere, arcu tortor lobortis diam, a porta ante leo ac ex. Sed eget mauris vel nunc pulvinar ultrices vel ut dolor. Proin egestas gravida nulla. Orci varius natoque penatibus et magnis dis parturient montes, nascetur ridiculus mus. Aenean dignissim neque sit amet sagittis convallis. Suspendisse vel diam magna. Donec sit amet nisi nisi. Ut tempus posuere nibh, ac condimentum justo commodo vitae. Suspendisse quis enim sit amet libero volutpat interdum ut ut dolor. Integer condimentum, lacus in dignissim fringilla, ligula felis mattis lectus, eu condimentum neque lorem a mi."
        }
    ],
    "results" : [
        {
            "date" : "August 7th",
            "home_party" : "FLA",
            "away_party" : "SFS",
            "result_home" : 1,
            "result_away" : 3
        },
        {
            "date" : "August 7th",
            "home_party" : "VAL",
            "away_party" : "SFS",
            "result_home" : 3,
            "result_away" : 2
        },
        {
            "date" : "August 7th",
            "home_party" : "SEO",
            "away_party" : "SHO",
            "result_home" : 4,
            "result_away" : 0
        },
        {
            "date" : "August 7th",
            "home_party" : "GLA",
            "away_party" : "LON",
            "result_home" : 3,
            "result_away" : 2
        },
        {
            "date" : "August 8th",
            "home_party" : "DAL",
            "away_party" : "HOU",
            "result_home" : 3,
            "result_away" : 2
        },
        {
            "date" : "August 8th",
            "home_party" : "NYE",
            "away_party" : "BOS",
            "result_home" : 3,
            "result_away" : 1
        },
        {
            "date" : "August 9th",
            "home_party" : "SFS",
            "away_party" : "LON",
            "result_home" : 0,
            "result_away" : 4
        },
        {
            "date" : "August 9th",
            "home_party" : "SEO",
            "away_party" : "HOU",
            "result_home" : 2,
            "result_away" : 1
        },
        {
            "date" : "August 9th",
            "home_party" : "SHO",
            "away_party" : "BOX",
            "result_home" : 2,
            "result_away" : 3
        },
        {
            "date" : "August 9th",
            "home_party" : "VAL",
            "away_party" : "GLA",
            "result_home" : 3,
            "result_away" : 1
        },
        {
            "date" : "August 9th",
            "home_party" : "FLA",
            "away_party" : "DAL",
            "result_home" : 1,
            "result_away" : 3
        },
        {
            "date" : "August 9th",
            "home_party" : "SEO",
            "away_party" : "NYE",
            "result_home" : 3,
            "result_away" : 1
        }
    ]
}